
{
  "response": {
  "version":"0.1",
  "termsofService":"http://www.wunderground.com/weather/api/d/terms.html",
  "features": {
  "history": 1
  }
	}
		,
	"history": {
		"date": {
		"pretty": "April 30, 2016",
		"year": "2016",
		"mon": "04",
		"mday": "30",
		"hour": "12",
		"min": "00",
		"tzname": "America/Los_Angeles"
		},
		"utcdate": {
		"pretty": "April 30, 2016",
		"year": "2016",
		"mon": "04",
		"mday": "30",
		"hour": "19",
		"min": "00",
		"tzname": "UTC"
		},
		"observations": [
		{
		"date": {
		"pretty": "12:56 AM PDT on April 30, 2016",
		"year": "2016",
		"mon": "04",
		"mday": "30",
		"hour": "00",
		"min": "56",
		"tzname": "America/Los_Angeles"
		},
		"utcdate": {
		"pretty": "7:56 AM GMT on April 30, 2016",
		"year": "2016",
		"mon": "04",
		"mday": "30",
		"hour": "07",
		"min": "56",
		"tzname": "UTC"
		},
		"tempm":"10.0", "tempi":"50.0","dewptm":"6.7", "dewpti":"44.1","hum":"80","wspdm":"27.8", "wspdi":"17.3","wgustm":"-9999.0", "wgusti":"-9999.0","wdird":"280","wdire":"West","vism":"16.1", "visi":"10.0","pressurem":"1014.3", "pressurei":"29.96","windchillm":"-999", "windchilli":"-999","heatindexm":"-9999", "heatindexi":"-9999","precipm":"-9999.00", "precipi":"-9999.00","conds":"Clear","icon":"clear","fog":"0","rain":"0","snow":"0","hail":"0","thunder":"0","tornado":"0","metar":"METAR KSFO 300756Z 28015KT 10SM CLR 10/07 A2996 RMK AO2 SLP143 T01000067 401560089" },
		{
		"date": {
		"pretty": "1:56 AM PDT on April 30, 2016",
		"year": "2016",
		"mon": "04",
		"mday": "30",
		"hour": "01",
		"min": "56",
		"tzname": "America/Los_Angeles"
		},
		"utcdate": {
		"pretty": "8:56 AM GMT on April 30, 2016",
		"year": "2016",
		"mon": "04",
		"mday": "30",
		"hour": "08",
		"min": "56",
		"tzname": "UTC"
		},
		"tempm":"9.4", "tempi":"48.9","dewptm":"6.7", "dewpti":"44.1","hum":"83","wspdm":"24.1", "wspdi":"15.0","wgustm":"-9999.0", "wgusti":"-9999.0","wdird":"270","wdire":"West","vism":"16.1", "visi":"10.0","pressurem":"1014.3", "pressurei":"29.96","windchillm":"-999", "windchilli":"-999","heatindexm":"-9999", "heatindexi":"-9999","precipm":"-9999.00", "precipi":"-9999.00","conds":"Clear","icon":"clear","fog":"0","rain":"0","snow":"0","hail":"0","thunder":"0","tornado":"0","metar":"METAR KSFO 300856Z 27013KT 10SM CLR 09/07 A2995 RMK AO2 SLP143 T00940067 50001" },
		{
		"date": {
		"pretty": "2:56 AM PDT on April 30, 2016",
		"year": "2016",
		"mon": "04",
		"mday": "30",
		"hour": "02",
		"min": "56",
		"tzname": "America/Los_Angeles"
		},
		"utcdate": {
		"pretty": "9:56 AM GMT on April 30, 2016",
		"year": "2016",
		"mon": "04",
		"mday": "30",
		"hour": "09",
		"min": "56",
		"tzname": "UTC"
		},
		"tempm":"10.0", "tempi":"50.0","dewptm":"6.1", "dewpti":"43.0","hum":"77","wspdm":"22.2", "wspdi":"13.8","wgustm":"-9999.0", "wgusti":"-9999.0","wdird":"280","wdire":"West","vism":"16.1", "visi":"10.0","pressurem":"1013.8", "pressurei":"29.94","windchillm":"-999", "windchilli":"-999","heatindexm":"-9999", "heatindexi":"-9999","precipm":"-9999.00", "precipi":"-9999.00","conds":"Clear","icon":"clear","fog":"0","rain":"0","snow":"0","hail":"0","thunder":"0","tornado":"0","metar":"METAR KSFO 300956Z 28012KT 10SM CLR 10/06 A2994 RMK AO2 SLP138 T01000061" },
		{
		"date": {
		"pretty": "3:56 AM PDT on April 30, 2016",
		"year": "2016",
		"mon": "04",
		"mday": "30",
		"hour": "03",
		"min": "56",
		"tzname": "America/Los_Angeles"
		},
		"utcdate": {
		"pretty": "10:56 AM GMT on April 30, 2016",
		"year": "2016",
		"mon": "04",
		"mday": "30",
		"hour": "10",
		"min": "56",
		"tzname": "UTC"
		},
		"tempm":"10.0", "tempi":"50.0","dewptm":"6.1", "dewpti":"43.0","hum":"77","wspdm":"25.9", "wspdi":"16.1","wgustm":"-9999.0", "wgusti":"-9999.0","wdird":"280","wdire":"West","vism":"16.1", "visi":"10.0","pressurem":"1013.5", "pressurei":"29.93","windchillm":"-999", "windchilli":"-999","heatindexm":"-9999", "heatindexi":"-9999","precipm":"-9999.00", "precipi":"-9999.00","conds":"Clear","icon":"clear","fog":"0","rain":"0","snow":"0","hail":"0","thunder":"0","tornado":"0","metar":"METAR KSFO 301056Z 28014KT 10SM CLR 10/06 A2993 RMK AO2 SLP135 T01000061" },
		{
		"date": {
		"pretty": "4:56 AM PDT on April 30, 2016",
		"year": "2016",
		"mon": "04",
		"mday": "30",
		"hour": "04",
		"min": "56",
		"tzname": "America/Los_Angeles"
		},
		"utcdate": {
		"pretty": "11:56 AM GMT on April 30, 2016",
		"year": "2016",
		"mon": "04",
		"mday": "30",
		"hour": "11",
		"min": "56",
		"tzname": "UTC"
		},
		"tempm":"9.4", "tempi":"48.9","dewptm":"6.1", "dewpti":"43.0","hum":"80","wspdm":"20.4", "wspdi":"12.7","wgustm":"-9999.0", "wgusti":"-9999.0","wdird":"280","wdire":"West","vism":"16.1", "visi":"10.0","pressurem":"1013.6", "pressurei":"29.94","windchillm":"-999", "windchilli":"-999","heatindexm":"-9999", "heatindexi":"-9999","precipm":"-9999.00", "precipi":"-9999.00","conds":"Clear","icon":"clear","fog":"0","rain":"0","snow":"0","hail":"0","thunder":"0","tornado":"0","metar":"METAR KSFO 301156Z 28011KT 10SM CLR 09/06 A2993 RMK AO2 SLP136 T00940061 10106 20094 55006" },
		{
		"date": {
		"pretty": "5:56 AM PDT on April 30, 2016",
		"year": "2016",
		"mon": "04",
		"mday": "30",
		"hour": "05",
		"min": "56",
		"tzname": "America/Los_Angeles"
		},
		"utcdate": {
		"pretty": "12:56 PM GMT on April 30, 2016",
		"year": "2016",
		"mon": "04",
		"mday": "30",
		"hour": "12",
		"min": "56",
		"tzname": "UTC"
		},
		"tempm":"9.4", "tempi":"48.9","dewptm":"5.6", "dewpti":"42.1","hum":"77","wspdm":"20.4", "wspdi":"12.7","wgustm":"-9999.0", "wgusti":"-9999.0","wdird":"280","wdire":"West","vism":"16.1", "visi":"10.0","pressurem":"1013.7", "pressurei":"29.94","windchillm":"-999", "windchilli":"-999","heatindexm":"-9999", "heatindexi":"-9999","precipm":"-9999.00", "precipi":"-9999.00","conds":"Partly Cloudy","icon":"partlycloudy","fog":"0","rain":"0","snow":"0","hail":"0","thunder":"0","tornado":"0","metar":"METAR KSFO 301256Z 28011KT 10SM FEW170 09/06 A2994 RMK AO2 SLP137 T00940056" },
		{
		"date": {
		"pretty": "6:56 AM PDT on April 30, 2016",
		"year": "2016",
		"mon": "04",
		"mday": "30",
		"hour": "06",
		"min": "56",
		"tzname": "America/Los_Angeles"
		},
		"utcdate": {
		"pretty": "1:56 PM GMT on April 30, 2016",
		"year": "2016",
		"mon": "04",
		"mday": "30",
		"hour": "13",
		"min": "56",
		"tzname": "UTC"
		},
		"tempm":"11.1", "tempi":"52.0","dewptm":"4.4", "dewpti":"39.9","hum":"63","wspdm":"11.1", "wspdi":"6.9","wgustm":"-9999.0", "wgusti":"-9999.0","wdird":"270","wdire":"West","vism":"16.1", "visi":"10.0","pressurem":"1013.9", "pressurei":"29.94","windchillm":"-999", "windchilli":"-999","heatindexm":"-9999", "heatindexi":"-9999","precipm":"-9999.00", "precipi":"-9999.00","conds":"Partly Cloudy","icon":"partlycloudy","fog":"0","rain":"0","snow":"0","hail":"0","thunder":"0","tornado":"0","metar":"METAR KSFO 301356Z 27006KT 10SM FEW200 11/04 A2994 RMK AO2 SLP139 T01110044" },
		{
		"date": {
		"pretty": "7:56 AM PDT on April 30, 2016",
		"year": "2016",
		"mon": "04",
		"mday": "30",
		"hour": "07",
		"min": "56",
		"tzname": "America/Los_Angeles"
		},
		"utcdate": {
		"pretty": "2:56 PM GMT on April 30, 2016",
		"year": "2016",
		"mon": "04",
		"mday": "30",
		"hour": "14",
		"min": "56",
		"tzname": "UTC"
		},
		"tempm":"14.4", "tempi":"57.9","dewptm":"3.3", "dewpti":"37.9","hum":"47","wspdm":"9.3", "wspdi":"5.8","wgustm":"-9999.0", "wgusti":"-9999.0","wdird":"260","wdire":"West","vism":"16.1", "visi":"10.0","pressurem":"1013.8", "pressurei":"29.94","windchillm":"-999", "windchilli":"-999","heatindexm":"-9999", "heatindexi":"-9999","precipm":"-9999.00", "precipi":"-9999.00","conds":"Partly Cloudy","icon":"partlycloudy","fog":"0","rain":"0","snow":"0","hail":"0","thunder":"0","tornado":"0","metar":"METAR KSFO 301456Z 26005KT 10SM FEW200 14/03 A2994 RMK AO2 SLP138 T01440033 50002" },
		{
		"date": {
		"pretty": "8:56 AM PDT on April 30, 2016",
		"year": "2016",
		"mon": "04",
		"mday": "30",
		"hour": "08",
		"min": "56",
		"tzname": "America/Los_Angeles"
		},
		"utcdate": {
		"pretty": "3:56 PM GMT on April 30, 2016",
		"year": "2016",
		"mon": "04",
		"mday": "30",
		"hour": "15",
		"min": "56",
		"tzname": "UTC"
		},
		"tempm":"16.7", "tempi":"62.1","dewptm":"2.8", "dewpti":"37.0","hum":"39","wspdm":"22.2", "wspdi":"13.8","wgustm":"-9999.0", "wgusti":"-9999.0","wdird":"330","wdire":"NNW","vism":"16.1", "visi":"10.0","pressurem":"1013.6", "pressurei":"29.94","windchillm":"-999", "windchilli":"-999","heatindexm":"-9999", "heatindexi":"-9999","precipm":"-9999.00", "precipi":"-9999.00","conds":"Partly Cloudy","icon":"partlycloudy","fog":"0","rain":"0","snow":"0","hail":"0","thunder":"0","tornado":"0","metar":"METAR KSFO 301556Z 33012KT 10SM FEW200 17/03 A2993 RMK AO2 SLP136 T01670028" },
		{
		"date": {
		"pretty": "9:56 AM PDT on April 30, 2016",
		"year": "2016",
		"mon": "04",
		"mday": "30",
		"hour": "09",
		"min": "56",
		"tzname": "America/Los_Angeles"
		},
		"utcdate": {
		"pretty": "4:56 PM GMT on April 30, 2016",
		"year": "2016",
		"mon": "04",
		"mday": "30",
		"hour": "16",
		"min": "56",
		"tzname": "UTC"
		},
		"tempm":"17.2", "tempi":"63.0","dewptm":"3.9", "dewpti":"39.0","hum":"41","wspdm":"27.8", "wspdi":"17.3","wgustm":"-9999.0", "wgusti":"-9999.0","wdird":"350","wdire":"North","vism":"16.1", "visi":"10.0","pressurem":"1012.9", "pressurei":"29.91","windchillm":"-999", "windchilli":"-999","heatindexm":"-9999", "heatindexi":"-9999","precipm":"-9999.00", "precipi":"-9999.00","conds":"Clear","icon":"clear","fog":"0","rain":"0","snow":"0","hail":"0","thunder":"0","tornado":"0","metar":"METAR KSFO 301656Z 35015KT 10SM CLR 17/04 A2991 RMK AO2 SLP129 T01720039" },
		{
		"date": {
		"pretty": "10:56 AM PDT on April 30, 2016",
		"year": "2016",
		"mon": "04",
		"mday": "30",
		"hour": "10",
		"min": "56",
		"tzname": "America/Los_Angeles"
		},
		"utcdate": {
		"pretty": "5:56 PM GMT on April 30, 2016",
		"year": "2016",
		"mon": "04",
		"mday": "30",
		"hour": "17",
		"min": "56",
		"tzname": "UTC"
		},
		"tempm":"18.9", "tempi":"66.0","dewptm":"3.9", "dewpti":"39.0","hum":"37","wspdm":"29.6", "wspdi":"18.4","wgustm":"-9999.0", "wgusti":"-9999.0","wdird":"340","wdire":"NNW","vism":"16.1", "visi":"10.0","pressurem":"1012.8", "pressurei":"29.91","windchillm":"-999", "windchilli":"-999","heatindexm":"-9999", "heatindexi":"-9999","precipm":"-9999.00", "precipi":"-9999.00","conds":"Clear","icon":"clear","fog":"0","rain":"0","snow":"0","hail":"0","thunder":"0","tornado":"0","metar":"METAR KSFO 301756Z 34016KT 10SM CLR 19/04 A2991 RMK AO2 SLP128 T01890039 10189 20094 56010" },
		{
		"date": {
		"pretty": "11:56 AM PDT on April 30, 2016",
		"year": "2016",
		"mon": "04",
		"mday": "30",
		"hour": "11",
		"min": "56",
		"tzname": "America/Los_Angeles"
		},
		"utcdate": {
		"pretty": "6:56 PM GMT on April 30, 2016",
		"year": "2016",
		"mon": "04",
		"mday": "30",
		"hour": "18",
		"min": "56",
		"tzname": "UTC"
		},
		"tempm":"20.6", "tempi":"69.1","dewptm":"3.9", "dewpti":"39.0","hum":"33","wspdm":"27.8", "wspdi":"17.3","wgustm":"-9999.0", "wgusti":"-9999.0","wdird":"280","wdire":"West","vism":"16.1", "visi":"10.0","pressurem":"1012.5", "pressurei":"29.90","windchillm":"-999", "windchilli":"-999","heatindexm":"-9999", "heatindexi":"-9999","precipm":"-9999.00", "precipi":"-9999.00","conds":"Clear","icon":"clear","fog":"0","rain":"0","snow":"0","hail":"0","thunder":"0","tornado":"0","metar":"METAR KSFO 301856Z 28015KT 10SM CLR 21/04 A2990 RMK AO2 SLP125 T02060039" },
		{
		"date": {
		"pretty": "12:56 PM PDT on April 30, 2016",
		"year": "2016",
		"mon": "04",
		"mday": "30",
		"hour": "12",
		"min": "56",
		"tzname": "America/Los_Angeles"
		},
		"utcdate": {
		"pretty": "7:56 PM GMT on April 30, 2016",
		"year": "2016",
		"mon": "04",
		"mday": "30",
		"hour": "19",
		"min": "56",
		"tzname": "UTC"
		},
		"tempm":"20.6", "tempi":"69.1","dewptm":"3.9", "dewpti":"39.0","hum":"33","wspdm":"33.3", "wspdi":"20.7","wgustm":"-9999.0", "wgusti":"-9999.0","wdird":"290","wdire":"WNW","vism":"16.1", "visi":"10.0","pressurem":"1012.0", "pressurei":"29.89","windchillm":"-999", "windchilli":"-999","heatindexm":"-9999", "heatindexi":"-9999","precipm":"-9999.00", "precipi":"-9999.00","conds":"Clear","icon":"clear","fog":"0","rain":"0","snow":"0","hail":"0","thunder":"0","tornado":"0","metar":"METAR KSFO 301956Z 29018KT 10SM CLR 21/04 A2989 RMK AO2 SLP120 T02060039" },
		{
		"date": {
		"pretty": "1:56 PM PDT on April 30, 2016",
		"year": "2016",
		"mon": "04",
		"mday": "30",
		"hour": "13",
		"min": "56",
		"tzname": "America/Los_Angeles"
		},
		"utcdate": {
		"pretty": "8:56 PM GMT on April 30, 2016",
		"year": "2016",
		"mon": "04",
		"mday": "30",
		"hour": "20",
		"min": "56",
		"tzname": "UTC"
		},
		"tempm":"21.1", "tempi":"70.0","dewptm":"5.0", "dewpti":"41.0","hum":"35","wspdm":"31.5", "wspdi":"19.6","wgustm":"-9999.0", "wgusti":"-9999.0","wdird":"290","wdire":"WNW","vism":"16.1", "visi":"10.0","pressurem":"1011.5", "pressurei":"29.87","windchillm":"-999", "windchilli":"-999","heatindexm":"-9999", "heatindexi":"-9999","precipm":"-9999.00", "precipi":"-9999.00","conds":"Clear","icon":"clear","fog":"0","rain":"0","snow":"0","hail":"0","thunder":"0","tornado":"0","metar":"METAR KSFO 302056Z 29017KT 10SM CLR 21/05 A2987 RMK AO2 SLP115 T02110050 58013" },
		{
		"date": {
		"pretty": "2:56 PM PDT on April 30, 2016",
		"year": "2016",
		"mon": "04",
		"mday": "30",
		"hour": "14",
		"min": "56",
		"tzname": "America/Los_Angeles"
		},
		"utcdate": {
		"pretty": "9:56 PM GMT on April 30, 2016",
		"year": "2016",
		"mon": "04",
		"mday": "30",
		"hour": "21",
		"min": "56",
		"tzname": "UTC"
		},
		"tempm":"20.6", "tempi":"69.1","dewptm":"6.1", "dewpti":"43.0","hum":"39","wspdm":"38.9", "wspdi":"24.2","wgustm":"-9999.0", "wgusti":"-9999.0","wdird":"280","wdire":"West","vism":"16.1", "visi":"10.0","pressurem":"1011.3", "pressurei":"29.87","windchillm":"-999", "windchilli":"-999","heatindexm":"-9999", "heatindexi":"-9999","precipm":"-9999.00", "precipi":"-9999.00","conds":"Partly Cloudy","icon":"partlycloudy","fog":"0","rain":"0","snow":"0","hail":"0","thunder":"0","tornado":"0","metar":"METAR KSFO 302156Z 28021KT 10SM FEW070 21/06 A2987 RMK AO2 SLP113 T02060061" },
		{
		"date": {
		"pretty": "3:56 PM PDT on April 30, 2016",
		"year": "2016",
		"mon": "04",
		"mday": "30",
		"hour": "15",
		"min": "56",
		"tzname": "America/Los_Angeles"
		},
		"utcdate": {
		"pretty": "10:56 PM GMT on April 30, 2016",
		"year": "2016",
		"mon": "04",
		"mday": "30",
		"hour": "22",
		"min": "56",
		"tzname": "UTC"
		},
		"tempm":"19.4", "tempi":"66.9","dewptm":"6.7", "dewpti":"44.1","hum":"44","wspdm":"37.0", "wspdi":"23.0","wgustm":"-9999.0", "wgusti":"-9999.0","wdird":"280","wdire":"West","vism":"16.1", "visi":"10.0","pressurem":"1010.5", "pressurei":"29.84","windchillm":"-999", "windchilli":"-999","heatindexm":"-9999", "heatindexi":"-9999","precipm":"-9999.00", "precipi":"-9999.00","conds":"Partly Cloudy","icon":"partlycloudy","fog":"0","rain":"0","snow":"0","hail":"0","thunder":"0","tornado":"0","metar":"METAR KSFO 302256Z 28020KT 10SM FEW200 19/07 A2984 RMK AO2 SLP105 T01940067" },
		{
		"date": {
		"pretty": "4:56 PM PDT on April 30, 2016",
		"year": "2016",
		"mon": "04",
		"mday": "30",
		"hour": "16",
		"min": "56",
		"tzname": "America/Los_Angeles"
		},
		"utcdate": {
		"pretty": "11:56 PM GMT on April 30, 2016",
		"year": "2016",
		"mon": "04",
		"mday": "30",
		"hour": "23",
		"min": "56",
		"tzname": "UTC"
		},
		"tempm":"18.9", "tempi":"66.0","dewptm":"7.2", "dewpti":"45.0","hum":"47","wspdm":"33.3", "wspdi":"20.7","wgustm":"-9999.0", "wgusti":"-9999.0","wdird":"280","wdire":"West","vism":"16.1", "visi":"10.0","pressurem":"1010.3", "pressurei":"29.84","windchillm":"-999", "windchilli":"-999","heatindexm":"-9999", "heatindexi":"-9999","precipm":"-9999.00", "precipi":"-9999.00","conds":"Partly Cloudy","icon":"partlycloudy","fog":"0","rain":"0","snow":"0","hail":"0","thunder":"0","tornado":"0","metar":"METAR KSFO 302356Z 28018KT 10SM FEW200 19/07 A2984 RMK AO2 PK WND 27026/2331 SLP103 T01890072 10217 20183 58012" },
		{
		"date": {
		"pretty": "5:56 PM PDT on April 30, 2016",
		"year": "2016",
		"mon": "04",
		"mday": "30",
		"hour": "17",
		"min": "56",
		"tzname": "America/Los_Angeles"
		},
		"utcdate": {
		"pretty": "12:56 AM GMT on May 01, 2016",
		"year": "2016",
		"mon": "05",
		"mday": "01",
		"hour": "00",
		"min": "56",
		"tzname": "UTC"
		},
		"tempm":"18.3", "tempi":"64.9","dewptm":"6.7", "dewpti":"44.1","hum":"47","wspdm":"37.0", "wspdi":"23.0","wgustm":"-9999.0", "wgusti":"-9999.0","wdird":"280","wdire":"West","vism":"16.1", "visi":"10.0","pressurem":"1010.3", "pressurei":"29.84","windchillm":"-999", "windchilli":"-999","heatindexm":"-9999", "heatindexi":"-9999","precipm":"-9999.00", "precipi":"-9999.00","conds":"Partly Cloudy","icon":"partlycloudy","fog":"0","rain":"0","snow":"0","hail":"0","thunder":"0","tornado":"0","metar":"METAR KSFO 010056Z 28020KT 10SM FEW200 18/07 A2983 RMK AO2 PK WND 28026/0042 SLP103 T01830067" },
		{
		"date": {
		"pretty": "6:56 PM PDT on April 30, 2016",
		"year": "2016",
		"mon": "04",
		"mday": "30",
		"hour": "18",
		"min": "56",
		"tzname": "America/Los_Angeles"
		},
		"utcdate": {
		"pretty": "1:56 AM GMT on May 01, 2016",
		"year": "2016",
		"mon": "05",
		"mday": "01",
		"hour": "01",
		"min": "56",
		"tzname": "UTC"
		},
		"tempm":"17.8", "tempi":"64.0","dewptm":"7.2", "dewpti":"45.0","hum":"50","wspdm":"29.6", "wspdi":"18.4","wgustm":"-9999.0", "wgusti":"-9999.0","wdird":"280","wdire":"West","vism":"16.1", "visi":"10.0","pressurem":"1009.9", "pressurei":"29.83","windchillm":"-999", "windchilli":"-999","heatindexm":"-9999", "heatindexi":"-9999","precipm":"-9999.00", "precipi":"-9999.00","conds":"Partly Cloudy","icon":"partlycloudy","fog":"0","rain":"0","snow":"0","hail":"0","thunder":"0","tornado":"0","metar":"METAR KSFO 010156Z 28016KT 10SM FEW200 18/07 A2982 RMK AO2 SLP099 T01780072" },
		{
		"date": {
		"pretty": "7:56 PM PDT on April 30, 2016",
		"year": "2016",
		"mon": "04",
		"mday": "30",
		"hour": "19",
		"min": "56",
		"tzname": "America/Los_Angeles"
		},
		"utcdate": {
		"pretty": "2:56 AM GMT on May 01, 2016",
		"year": "2016",
		"mon": "05",
		"mday": "01",
		"hour": "02",
		"min": "56",
		"tzname": "UTC"
		},
		"tempm":"16.1", "tempi":"61.0","dewptm":"7.2", "dewpti":"45.0","hum":"56","wspdm":"29.6", "wspdi":"18.4","wgustm":"-9999.0", "wgusti":"-9999.0","wdird":"280","wdire":"West","vism":"16.1", "visi":"10.0","pressurem":"1010.1", "pressurei":"29.83","windchillm":"-999", "windchilli":"-999","heatindexm":"-9999", "heatindexi":"-9999","precipm":"-9999.00", "precipi":"-9999.00","conds":"Partly Cloudy","icon":"partlycloudy","fog":"0","rain":"0","snow":"0","hail":"0","thunder":"0","tornado":"0","metar":"METAR KSFO 010256Z 28016KT 10SM FEW200 16/07 A2983 RMK AO2 SLP101 T01610072 55002" },
		{
		"date": {
		"pretty": "8:56 PM PDT on April 30, 2016",
		"year": "2016",
		"mon": "04",
		"mday": "30",
		"hour": "20",
		"min": "56",
		"tzname": "America/Los_Angeles"
		},
		"utcdate": {
		"pretty": "3:56 AM GMT on May 01, 2016",
		"year": "2016",
		"mon": "05",
		"mday": "01",
		"hour": "03",
		"min": "56",
		"tzname": "UTC"
		},
		"tempm":"16.1", "tempi":"61.0","dewptm":"7.2", "dewpti":"45.0","hum":"56","wspdm":"27.8", "wspdi":"17.3","wgustm":"-9999.0", "wgusti":"-9999.0","wdird":"280","wdire":"West","vism":"16.1", "visi":"10.0","pressurem":"1010.2", "pressurei":"29.83","windchillm":"-999", "windchilli":"-999","heatindexm":"-9999", "heatindexi":"-9999","precipm":"-9999.00", "precipi":"-9999.00","conds":"Clear","icon":"clear","fog":"0","rain":"0","snow":"0","hail":"0","thunder":"0","tornado":"0","metar":"METAR KSFO 010356Z 28015KT 10SM CLR 16/07 A2983 RMK AO2 SLP102 T01610072" },
		{
		"date": {
		"pretty": "9:56 PM PDT on April 30, 2016",
		"year": "2016",
		"mon": "04",
		"mday": "30",
		"hour": "21",
		"min": "56",
		"tzname": "America/Los_Angeles"
		},
		"utcdate": {
		"pretty": "4:56 AM GMT on May 01, 2016",
		"year": "2016",
		"mon": "05",
		"mday": "01",
		"hour": "04",
		"min": "56",
		"tzname": "UTC"
		},
		"tempm":"15.6", "tempi":"60.1","dewptm":"7.2", "dewpti":"45.0","hum":"57","wspdm":"24.1", "wspdi":"15.0","wgustm":"-9999.0", "wgusti":"-9999.0","wdird":"270","wdire":"West","vism":"16.1", "visi":"10.0","pressurem":"1010.4", "pressurei":"29.84","windchillm":"-999", "windchilli":"-999","heatindexm":"-9999", "heatindexi":"-9999","precipm":"-9999.00", "precipi":"-9999.00","conds":"Clear","icon":"clear","fog":"0","rain":"0","snow":"0","hail":"0","thunder":"0","tornado":"0","metar":"METAR KSFO 010456Z 27013KT 10SM CLR 16/07 A2984 RMK AO2 SLP104 T01560072" },
		{
		"date": {
		"pretty": "10:56 PM PDT on April 30, 2016",
		"year": "2016",
		"mon": "04",
		"mday": "30",
		"hour": "22",
		"min": "56",
		"tzname": "America/Los_Angeles"
		},
		"utcdate": {
		"pretty": "5:56 AM GMT on May 01, 2016",
		"year": "2016",
		"mon": "05",
		"mday": "01",
		"hour": "05",
		"min": "56",
		"tzname": "UTC"
		},
		"tempm":"16.7", "tempi":"62.1","dewptm":"6.7", "dewpti":"44.1","hum":"52","wspdm":"18.5", "wspdi":"11.5","wgustm":"-9999.0", "wgusti":"-9999.0","wdird":"270","wdire":"West","vism":"16.1", "visi":"10.0","pressurem":"1010.1", "pressurei":"29.83","windchillm":"-999", "windchilli":"-999","heatindexm":"-9999", "heatindexi":"-9999","precipm":"-9999.00", "precipi":"-9999.00","conds":"Clear","icon":"clear","fog":"0","rain":"0","snow":"0","hail":"0","thunder":"0","tornado":"0","metar":"METAR KSFO 010556Z 27010KT 10SM CLR 17/07 A2983 RMK AO2 SLP101 T01670067 10194 20156 50000" },
		{
		"date": {
		"pretty": "11:56 PM PDT on April 30, 2016",
		"year": "2016",
		"mon": "04",
		"mday": "30",
		"hour": "23",
		"min": "56",
		"tzname": "America/Los_Angeles"
		},
		"utcdate": {
		"pretty": "6:56 AM GMT on May 01, 2016",
		"year": "2016",
		"mon": "05",
		"mday": "01",
		"hour": "06",
		"min": "56",
		"tzname": "UTC"
		},
		"tempm":"17.2", "tempi":"63.0","dewptm":"9.4", "dewpti":"48.9","hum":"60","wspdm":"9.3", "wspdi":"5.8","wgustm":"-9999.0", "wgusti":"-9999.0","wdird":"350","wdire":"North","vism":"16.1", "visi":"10.0","pressurem":"1010.0", "pressurei":"29.83","windchillm":"-999", "windchilli":"-999","heatindexm":"-9999", "heatindexi":"-9999","precipm":"-9999.00", "precipi":"-9999.00","conds":"Clear","icon":"clear","fog":"0","rain":"0","snow":"0","hail":"0","thunder":"0","tornado":"0","metar":"METAR KSFO 010656Z 35005KT 10SM CLR 17/09 A2983 RMK AO2 SLP100 T01720094" }
		],
		"dailysummary": [
		{ "date": {
		"pretty": "12:00 PM PDT on April 30, 2016",
		"year": "2016",
		"mon": "04",
		"mday": "30",
		"hour": "12",
		"min": "00",
		"tzname": "America/Los_Angeles"
		},
		"fog":"0","rain":"0","snow":"0","snowfallm":"0.00", "snowfalli":"0.00","monthtodatesnowfallm":"0.00", "monthtodatesnowfalli":"0.00","since1julsnowfallm":"0.00", "since1julsnowfalli":"0.00","snowdepthm":"", "snowdepthi":"","hail":"0","thunder":"0","tornado":"0","meantempm":"16", "meantempi":"60","meandewptm":"6", "meandewpti":"43","meanpressurem":"1012", "meanpressurei":"29.89","meanwindspdm":"25", "meanwindspdi":"16","meanwdire":"","meanwdird":"287","meanvism":"16", "meanvisi":"10","humidity":"","maxtempm":"22", "maxtempi":"71","mintempm":"9", "mintempi":"49","maxhumidity":"86","minhumidity":"33","maxdewptm":"9", "maxdewpti":"49","mindewptm":"3", "mindewpti":"37","maxpressurem":"1014", "maxpressurei":"29.96","minpressurem":"1010", "minpressurei":"29.83","maxwspdm":"42", "maxwspdi":"26","minwspdm":"10", "minwspdi":"6","maxvism":"16", "maxvisi":"10","minvism":"16", "minvisi":"10","gdegreedays":"10","heatingdegreedays":"5","coolingdegreedays":"0","precipm":"0.00", "precipi":"0.00","precipsource":"","heatingdegreedaysnormal":"7","monthtodateheatingdegreedays":"153","monthtodateheatingdegreedaysnormal":"247","since1sepheatingdegreedays":"","since1sepheatingdegreedaysnormal":"","since1julheatingdegreedays":"1768","since1julheatingdegreedaysnormal":"2368","coolingdegreedaysnormal":"0","monthtodatecoolingdegreedays":"20","monthtodatecoolingdegreedaysnormal":"5","since1sepcoolingdegreedays":"","since1sepcoolingdegreedaysnormal":"","since1jancoolingdegreedays":"20","since1jancoolingdegreedaysnormal":"6" }
		]
	}
}
